autograders/__init__.py
autograders-0.1.1.dist-info/METADATA
autograders-0.1.1.dist-info/WHEEL
autograders-0.1.1.dist-info/top_level.txt
autograders-0.1.1.dist-info/RECORD
