Metadata-Version: 2.4
Name: autograders
Version: 0.1.1
Summary: A minimal autograders package
Author-email: Joseph Camyre <joseph@judgmentlabs.ai>
License: MIT
Classifier: Programming Language :: Python :: 3
Classifier: License :: OSI Approved :: MIT License
Classifier: Operating System :: OS Independent
Requires-Python: >=3.9
